{
    "batch_size": 5,
    "sequencer_url": "https://postman-echo.com",
    "prometheus_url": "127.0.0.1:8080",
    "poll_period_ms": 5000,
    "secret_key_path": "/home/stefan/repos/blocksense/apps/reporter/reporter_secret_key",
    "resources": {
      "CMC_API_KEY_PATH": "/home/stefan/repos/blocksense/apps/reporter/CMC_API_KEY"
    },
    "reporter" : {"id": 0, "pub_key": "ea30af86b930d539c55677b05b4a5dad9fce1f758ba09d152d19a7d6940f8d8a8a8fb9f90d38a19e988d721cddaee4567d2e" },
    "feeds" : [
      {"id": 0, "name": "CoinMarketCap.DOGE", "report_interval_ms": 60000, "first_report_start_time": {"secs_since_epoch":0, "nanos_since_epoch": 0}},
      {"id": 1, "name": "CoinMarketCap.BTC", "report_interval_ms": 60000, "first_report_start_time": {"secs_since_epoch":0, "nanos_since_epoch": 0}},
      {"id": 2, "name": "CoinMarketCap.ETH", "report_interval_ms": 60000, "first_report_start_time": {"secs_since_epoch":0, "nanos_since_epoch": 0}},
      {"id": 3, "name": "CoinMarketCap.SHIB", "report_interval_ms": 60000, "first_report_start_time": {"secs_since_epoch":0, "nanos_since_epoch": 0}},
      {"id": 4, "name": "CoinMarketCap.SOL", "report_interval_ms": 60000, "first_report_start_time": {"secs_since_epoch":0, "nanos_since_epoch": 0}},
      {"id": 5, "name": "CoinMarketCap.DOT", "report_interval_ms": 60000, "first_report_start_time": {"secs_since_epoch":0, "nanos_since_epoch": 0}},
      {"id": 6, "name": "CoinMarketCap.XRP", "report_interval_ms": 60000, "first_report_start_time": {"secs_since_epoch":0, "nanos_since_epoch": 0}},
      {"id": 7, "name": "YahooFinance.AAPL", "report_interval_ms": 60000, "first_report_start_time": {"secs_since_epoch":0, "nanos_since_epoch": 0}},
      {"id": 8, "name": "YahooFinance.GOOGL", "report_interval_ms": 60000, "first_report_start_time": {"secs_since_epoch":0, "nanos_since_epoch": 0}},
      {"id": 9, "name": "YahooFinance.TSLA", "report_interval_ms": 60000, "first_report_start_time": {"secs_since_epoch":0, "nanos_since_epoch": 0}},
      {"id": 10, "name": "YahooFinance.IBKR", "report_interval_ms": 60000, "first_report_start_time": {"secs_since_epoch":0, "nanos_since_epoch": 0}},
      {"id": 11, "name": "YahooFinance.NVDA", "report_interval_ms": 60000, "first_report_start_time": {"secs_since_epoch":0, "nanos_since_epoch": 0}},
      {"id": 12, "name": "YahooFinance.TLRY", "report_interval_ms": 60000, "first_report_start_time": {"secs_since_epoch":0, "nanos_since_epoch": 0}},
      {"id": 13, "name": "YahooFinance.AMD", "report_interval_ms": 60000, "first_report_start_time": {"secs_since_epoch":0, "nanos_since_epoch": 0}}
    ]
}
